{
  "$schema": "https://json-schema.org/draft/2020-12/schema",
  "$id": "https://astro-plan.local/contracts/inbox.classify.json",
  "title": "inbox.classify",
  "description": "Classify an Inbox folder as single_type, mixed, or unclassified using deterministic IMAGETYP-based evidence. Idempotent unless force_rescan is true. Returns a contentSignature that must be supplied to inbox.confirm to guard against TOCTOU drift.",
  "type": "object",
  "version": "1.1.0",
  "operation": "inbox.classify",
  "request": {
    "type": "object",
    "required": ["inbox_item_id"],
    "additionalProperties": false,
    "properties": {
      "inbox_item_id": {
        "type": "string",
        "description": "Stable identifier of the Inbox folder candidate."
      },
      "force_rescan": {
        "type": "boolean",
        "default": false,
        "description": "If true, invalidate cached metadata for this Inbox item and re-read headers from disk."
      }
    }
  },
  "response": {
    "type": "object",
    "required": ["inbox_item_id", "type", "content_signature", "computed_at"],
    "additionalProperties": false,
    "properties": {
      "inbox_item_id": { "type": "string" },
      "type": {
        "type": "string",
        "enum": ["single_type", "mixed", "unclassified"]
      },
      "content_signature": {
        "type": "string",
        "description": "Folder-level signature computed per R-Sig-1 (sha256 of sorted per-file signatures). Must be supplied to inbox.confirm to guard against TOCTOU drift. (Ref: A8, R-Sig-1)"
      },
      "frame_type": {
        "type": "string",
        "enum": ["light", "dark", "bias", "flat", "dark_flat"],
        "description": "Present only when type == single_type."
      },
      "breakdown": {
        "type": "array",
        "description": "Present when type in {single_type, mixed}.",
        "items": {
          "type": "object",
          "required": ["kind", "count"],
          "additionalProperties": false,
          "properties": {
            "kind": {
              "type": "string",
              "enum": ["light", "dark", "bias", "flat", "dark_flat"]
            },
            "count": { "type": "integer", "minimum": 0 },
            "destination_preview": {
              "type": "string",
              "description": "Path preview produced by the active Naming & Structure pattern. Preview only; the canonical destination is resolved at plan generation time."
            },
            "sample_files": {
              "type": "array",
              "items": { "type": "string" },
              "maxItems": 10
            }
          }
        }
      },
      "unclassified_files": {
        "type": "array",
        "description": "Relative file paths where IMAGETYP was absent, unreadable, or did not match any normalization entry. These files have per-file unclassified markers and are surfaced in the UI as 'Needs review'. (Ref: R-FileMarker)",
        "items": { "type": "string" }
      },
      "sample_files": {
        "type": "array",
        "description": "Representative filenames spanning the folder.",
        "items": { "type": "string" },
        "maxItems": 10
      },
      "computed_at": {
        "type": "string",
        "format": "date-time"
      }
    }
  },
  "errors": [
    {
      "code": "inbox.item.not_found",
      "description": "No InboxItem exists for the provided inbox_item_id.",
      "http_status_hint": 404
    },
    {
      "code": "metadata.unreadable",
      "description": "Folder is reachable but no file metadata could be read (permissions, corruption, missing mount).",
      "http_status_hint": 422,
      "data": {
        "type": "object",
        "properties": {
          "unreadable_count": { "type": "integer" },
          "total_count": { "type": "integer" }
        }
      }
    }
  ]
}
